time_magic/__init__.py
time_magic/life_in_weeks.py
time_magic/seven_years_circle.py
time_magic/timebill.py
time_magic-0.3.3.dist-info/LICENSE
time_magic-0.3.3.dist-info/METADATA
time_magic-0.3.3.dist-info/WHEEL
time_magic-0.3.3.dist-info/top_level.txt
time_magic-0.3.3.dist-info/RECORD
